odoo/addons/transfer_client_portfolio_commissions/README.rst
odoo/addons/transfer_client_portfolio_commissions/__init__.py
odoo/addons/transfer_client_portfolio_commissions/__manifest__.py
odoo/addons/transfer_client_portfolio_commissions/i18n/es.po
odoo/addons/transfer_client_portfolio_commissions/models/__init__.py
odoo/addons/transfer_client_portfolio_commissions/models/portfolio_transfer_registry.py
odoo/addons/transfer_client_portfolio_commissions/readme/CONTRIBUTORS.md
odoo/addons/transfer_client_portfolio_commissions/readme/DESCRIPTION.md
odoo/addons/transfer_client_portfolio_commissions/readme/USAGE.md
odoo/addons/transfer_client_portfolio_commissions/static/description/icon.png
odoo/addons/transfer_client_portfolio_commissions/static/description/index.html
odoo/addons/transfer_client_portfolio_commissions/tests/__init__.py
odoo/addons/transfer_client_portfolio_commissions/tests/test_transfer_client_portfolio_commissions.py
odoo/addons/transfer_client_portfolio_commissions/views/portfolio_transfer_registry_views.xml
odoo/addons/transfer_client_portfolio_commissions/wizard/__init__.py
odoo/addons/transfer_client_portfolio_commissions/wizard/transfer_portfolio_wizard_views.xml
odoo/addons/transfer_client_portfolio_commissions/wizard/trasnfer_portfolio_wizard.py
odoo_addon_transfer_client_portfolio_commissions-15.0.1.0.2.3.dist-info/METADATA
odoo_addon_transfer_client_portfolio_commissions-15.0.1.0.2.3.dist-info/WHEEL
odoo_addon_transfer_client_portfolio_commissions-15.0.1.0.2.3.dist-info/top_level.txt
odoo_addon_transfer_client_portfolio_commissions-15.0.1.0.2.3.dist-info/RECORD
